{
    "frames": { 
        "openTile8": {
            "frame": {
                "x": 0,
                "y": 40,
                "w": 64,
                "h": 64
            }
        }, 
        "openTile7": {
            "frame": {
                "x": 0,
                "y": 104,
                "w": 64,
                "h": 64
            }
        },
        "openTile6": {
            "frame": {
                "x": 0,
                "y": 168,
                "w": 64,
                "h": 64
            }
        },
        "openTile5": {
            "frame": {
                "x": 0,
                "y": 232,
                "w": 64,
                "h": 64
            }
        },
        "openTile4": {
            "frame": {
                "x": 0,
                "y": 296,
                "w": 64,
                "h": 64
            }
        },
        "openTile3": {
            "frame": {
                "x": 0,
                "y": 360,
                "w": 64,
                "h": 64
            }
        },
        "openTile2": {
            "frame": {
                "x": 0,
                "y": 424,
                "w": 64,
                "h": 64
            }
        },
        "openTile1": {
            "frame": {
                "x": 0,
                "y": 488,
                "w": 64,
                "h": 64
            }
        },
        "openTile0": {
            "frame": {
                "x": 0,
                "y": 552,
                "w": 64,
                "h": 64
            }
        },
        "openBomb": {
            "frame": {
                "x": 0,
                "y": 616,
                "w": 64,
                "h": 64
            }
        },
        "closedTile": {
            "frame": {
                "x": 0,
                "y": 680,
                "w": 64,
                "h": 64
            }
        },
        "openBombRed": {
            "frame": {
                "x": 0,
                "y": 744,
                "w": 64,
                "h": 64
            }
        },
        "openBombCross": {
            "frame": {
                "x": 0,
                "y": 808,
                "w": 64,
                "h": 64
            }
        },
        "flag": {
            "frame": {
                "x": 0,
                "y": 871,
                "w": 64,
                "h": 64
            }
        },

        "score8": {
            "frame": {
                "x": 65,
                "y": 0,
                "w": 59,
                "h": 109
            }
        },
        "score6": {
            "frame": {
                "x": 65,
                "y": 109,
                "w": 59,
                "h": 109
            }
        },
        "score4": {
            "frame": {
                "x": 65,
                "y": 218,
                "w": 59,
                "h": 109
            }
        },
        "score2": {
            "frame": {
                "x": 65,
                "y": 327,
                "w": 59,
                "h": 109
            }
        },
        "score0": {
            "frame": {
                "x": 65,
                "y": 436,
                "w": 59,
                "h": 109
            }
        },
        "score9": {
            "frame": {
                "x": 65,
                "y": 0,
                "w": 59,
                "h": 109
            }
        },
        "score7": {
            "frame": {
                "x": 65,
                "y": 109,
                "w": 59,
                "h": 109
            }
        },
        "score5": {
            "frame": {
                "x": 65,
                "y": 218,
                "w": 59,
                "h": 109
            }
        },
        "score3": {
            "frame": {
                "x": 65,
                "y": 327,
                "w": 59,
                "h": 109
            }
        },
        "score1": {
            "frame": {
                "x": 65,
                "y": 436,
                "w": 59,
                "h": 109
            }
        },
        "smileScared": {
            "frame": {
                "x": 64,
                "y": 545,
                "w": 130,
                "h": 130
            }
        },
        "smile": {
            "frame": {
                "x": 64,
                "y": 675,
                "w": 130,
                "h": 130
            }
        },
        "smileCool": {
            "frame": {
                "x": 64,
                "y": 805,
                "w": 130,
                "h": 130
            }
        }
    },
    "meta": {
        "image": "sprites.png",
        "format": "RGBA8888",
        "size": {
            "w": 194,
            "h": 935
        },
        "scale": "1"
    }
}